cytosummarynet/__init__.py
cytosummarynet/dataset.py
cytosummarynet/engine.py
cytosummarynet/models.py
cytosummarynet/py.typed
cytosummarynet-0.0.4.dist-info/METADATA
cytosummarynet-0.0.4.dist-info/WHEEL
cytosummarynet-0.0.4.dist-info/RECORD
