Metadata-Version: 2.4
Name: cytosummarynet
Version: 0.0.4
Summary: Capturing cell heterogeneity in representations of cell populations for image-based profiling using contrastive learning
Author-email: Shantanu Singh <shsingh@broadinstitute.org>
Requires-Python: >=3.10
Requires-Dist: numpy>=2.2.0
Requires-Dist: pandas>=2.2.3
Requires-Dist: pytorch-metric-learning>=2.8.1
Requires-Dist: torch>=2.5.1
Requires-Dist: tqdm>=4.67.1
